simulation/add_sub_8bit.v
//==============================
// Top-level module for DE2 board
//==============================
module top_add_sub_8bit (
    input  [15:0] SW,       // SW[7:0] = A, SW[15:8] = B
    input  [3:0]  KEY,      // KEY[0]=Add/Sub, KEY[1]=Sel, KEY[3]=Clock
    output [6:0]  HEX0,     // A lower
    output [6:0]  HEX1,     // A upper
    output [6:0]  HEX2,     // B lower
    output [6:0]  HEX3,     // B upper
    output [6:0]  HEX4,     // Z lower
    output [6:0]  HEX5,     // Z upper
    output [7:0]  LEDR,     // Result in binary
    output [1:0]  LEDG      // LEDG[0]=Overflow, LEDG[1]=Carryout
);

    wire [7:0] A, B, Z;
    wire Sel, AddSub, clk;
    wire Overflow, Carryout;

    assign A = SW[7:0];
    assign B = SW[15:8];
    assign AddSub = KEY[0];
    assign Sel = KEY[1];
    assign clk = ~KEY[3];   // KEY active-low, đảo lại để có xung clock dương

    // Instantiate main adder/subtractor
    add_sub_8bit core (
        .clk(clk),
        .A(A),
        .B(B),
        .Sel(Sel),
        .AddSub(AddSub),
        .Z(Z),
        .Overflow(Overflow),
        .Carryout(Carryout)
    );

    // Hiển thị kết quả
    assign LEDR = Z;
    assign LEDG[0] = Overflow;
    assign LEDG[1] = Carryout;

    // Hiển thị lên 7-seg
    hex7seg h0(A[3:0], HEX0);
    hex7seg h1(A[7:4], HEX1);
    hex7seg h2(B[3:0], HEX2);
    hex7seg h3(B[7:4], HEX3);
    hex7seg h4(Z[3:0], HEX4);
    hex7seg h5(Z[7:4], HEX5);

endmodule


//==============================
// Core logic 8-bit adder/subtractor with accumulator
//==============================
module add_sub_8bit (
    input clk,
    input [7:0] A, B,
    input Sel,       // 0: A ± B, 1: Z ± B (accumulate)
    input AddSub,    // 0: Add, 1: Sub
    output reg [7:0] Z,
    output reg Overflow,
    output reg Carryout
);
    reg [7:0] Areg, Breg, Zreg;
    reg SelR, AddSubR;
    wire [7:0] G, H, M;
    wire carryin, carryout;
    wire over_flow;

    // Đưa dữ liệu vào thanh ghi tại cạnh dương xung clock
    always @(posedge clk) begin
        Areg <= A;
        Breg <= B;
        SelR <= Sel;
        AddSubR <= AddSub;
    end

    assign carryin = AddSubR;
    assign H = Breg ^ {8{AddSubR}};  // đảo bit B khi trừ
    assign G = SelR ? Zreg : Areg;   // chọn A hoặc Z (accumulate)
    assign {carryout, M} = G + H + carryin;

    // Phát hiện overflow
    assign over_flow = (G[7] & H[7] & ~M[7]) | (~G[7] & ~H[7] & M[7]);

    // Ghi kết quả vào Zreg
    always @(posedge clk) begin
		Zreg <= M;
		Z <= M;  // <-- cập nhật trực tiếp thay vì Zreg
		Overflow <= over_flow;
		Carryout <= carryout;

    end
endmodule


//==============================
// 7-segment decoder module
//==============================
module hex7seg (
    input [3:0] hex,
    output reg [6:0] seg
);
    always @(*) begin
        case (hex)
            4'h0: seg = 7'b1000000;
            4'h1: seg = 7'b1111001;
            4'h2: seg = 7'b0100100;
            4'h3: seg = 7'b0110000;
            4'h4: seg = 7'b0011001;
            4'h5: seg = 7'b0010010;
            4'h6: seg = 7'b0000010;
            4'h7: seg = 7'b1111000;
            4'h8: seg = 7'b0000000;
            4'h9: seg = 7'b0010000;
            4'hA: seg = 7'b0001000;
            4'hB: seg = 7'b0000011;
            4'hC: seg = 7'b1000110;
            4'hD: seg = 7'b0100001;
            4'hE: seg = 7'b0000110;
            4'hF: seg = 7'b0001110;
            default: seg = 7'b1111111;
        endcase
    end
endmodule

simulation/tb_add_sub_8bit.v
`timescale 1ns/1ps
module tb_add_sub_8bit;
    reg clk;
    reg [7:0] A, B;
    reg Sel, AddSub;
    wire [7:0] Z;
    wire Overflow, Carryout;

    // Instantiate DUT
    add_sub_8bit DUT (
        .clk(clk),
        .A(A),
        .B(B),
        .Sel(Sel),
        .AddSub(AddSub),
        .Z(Z),
        .Overflow(Overflow),
        .Carryout(Carryout)
    );

    // Clock generator: 10ns period (100MHz)
    initial begin
        clk = 0;
        forever #5 clk = ~clk;
    end

    // In ra console khi có thay đổi
    initial begin
        $display("Time(ns)\tSel\tAddSub\tA\tB\tZ\tCarry\tOverflow");
        $monitor("%0dns\t%b\t%b\t%d\t%d\t%d\t%b\t%b",
                 $time, Sel, AddSub, A, B, Z, Carryout, Overflow);
    end

    // Simulation scenario
    initial begin
        $dumpfile("add_sub_8bit.vcd");   // output waveform file
        $dumpvars(0, tb_add_sub_8bit);

        // Case 1: Add
        A = 8'd25; B = 8'd10; Sel = 0; AddSub = 0; #20;

        // Case 2: Subtract
        A = 8'd40; B = 8'd15; Sel = 0; AddSub = 1; #20;

        // Case 3: Accumulate mode (add)
        Sel = 1; B = 8'd5; AddSub = 0; #20;

        // Case 4: Subtract in accumulate mode
        Sel = 1; B = 8'd3; AddSub = 1; #20;

        $display("=== Simulation Finished ===");
        $finish;
    end
endmodule

simulation/add_sub_8bit.vcd
$date
	Sun Nov 02 16:03:53 2025
$end
$version
	Icarus Verilog
$end
$timescale
	1ps
$end
$scope module tb_add_sub_8bit $end
$var wire 8 ! Z [7:0] $end
$var wire 1 " Overflow $end
$var wire 1 # Carryout $end
$var reg 8 $ A [7:0] $end
$var reg 1 % AddSub $end
$var reg 8 & B [7:0] $end
$var reg 1 ' Sel $end
$var reg 1 ( clk $end
$scope module DUT $end
$var wire 8 ) A [7:0] $end
$var wire 1 % AddSub $end
$var wire 8 * B [7:0] $end
$var wire 8 + H [7:0] $end
$var wire 1 ' Sel $end
$var wire 1 , carryin $end
$var wire 1 ( clk $end
$var wire 1 - over_flow $end
$var wire 1 . carryout $end
$var wire 8 / M [7:0] $end
$var wire 8 0 G [7:0] $end
$var reg 1 1 AddSubR $end
$var reg 8 2 Areg [7:0] $end
$var reg 8 3 Breg [7:0] $end
$var reg 1 # Carryout $end
$var reg 1 " Overflow $end
$var reg 1 4 SelR $end
$var reg 8 5 Z [7:0] $end
$var reg 8 6 Zreg [7:0] $end
$upscope $end
$upscope $end
$enddefinitions $end
#0
$dumpvars
bx 6
bx 5
x4
bx 3
bx 2
x1
bx 0
bx /
x.
x-
x,
bx +
b1010 *
b11001 )
0(
0'
b1010 &
0%
b11001 $
x#
x"
bx !
$end
#5000
0-
b100011 /
0.
b1010 +
b11001 0
0,
01
04
b1010 3
b11001 2
1(
#10000
0(
#15000
0#
0"
b100011 !
b100011 5
b100011 6
1(
#20000
0(
1%
b1111 &
b1111 *
b101000 $
b101000 )
#25000
1.
b11001 /
b11110000 +
b101000 0
1,
11
b1111 3
b101000 2
1(
#30000
0(
#35000
1#
b11001 !
b11001 5
b11001 6
1(
#40000
0(
0%
b101 &
b101 *
1'
#45000
0.
b11110 /
b11001 0
b101 +
0,
01
14
b101 3
1(
#50000
0(
#55000
b100011 /
b11110 0
0#
b11110 !
b11110 5
b11110 6
1(
#60000
0(
1%
b11 &
b11 *
#65000
1.
b100000 /
b11111100 +
b100011 0
1,
11
b11 3
b100011 !
b100011 5
b100011 6
1(
#70000
0(
#75000
b11101 /
b100000 0
1#
b100000 !
b100000 5
b100000 6
1(
